mango/__init__.py
mango/benchmark/__init__.py
mango/benchmark/optimization/__init__.py
mango/benchmark/optimization/ackley.py
mango/benchmark/optimization/bukin.py
mango/benchmark/optimization/cross_in_tray.py
mango/benchmark/optimization/dolan.py
mango/benchmark/optimization/drop_wave.py
mango/benchmark/optimization/egg_holder.py
mango/benchmark/optimization/gramacy_lee.py
mango/benchmark/optimization/griewank.py
mango/benchmark/optimization/holder_table.py
mango/benchmark/optimization/langermann.py
mango/benchmark/optimization/levy.py
mango/benchmark/optimization/rastrigin.py
mango/benchmark/optimization/rosenbrock.py
mango/benchmark/optimization/schaffer.py
mango/benchmark/optimization/schwefel.py
mango/clients/__init__.py
mango/clients/aemet.py
mango/clients/arcgis.py
mango/clients/cloud_storage.py
mango/clients/email_downloader.py
mango/clients/email_sender.py
mango/clients/google_cloud_storage.py
mango/clients/rest_client.py
mango/config/__init__.py
mango/config/base_config.py
mango/decodoc/__init__.py
mango/decodoc/decodoc.py
mango/logging/__init__.py
mango/logging/chrono.py
mango/logging/decorators.py
mango/logging/logger.py
mango/models/__init__.py
mango/models/pyomo.py
mango/processing/__init__.py
mango/processing/data_imputer.py
mango/processing/date_functions.py
mango/processing/file_functions.py
mango/processing/object_functions.py
mango/schemas/location.json
mango/shared/__init__.py
mango/shared/const.py
mango/shared/decorators.py
mango/shared/exceptions.py
mango/shared/requirement_check.py
mango/shared/spatial.py
mango/table/__init__.py
mango/table/pytups_table.py
mango/table/pytups_tools.py
mango/table/table_tools.py
mango/tests/__init__.py
mango/tests/const.py
mango/tests/clients_module/__init__.py
mango/tests/clients_module/test_aemet_client.py
mango/tests/clients_module/test_arcgis_client.py
mango/tests/clients_module/test_rest_client.py
mango/tests/config_module/__init__.py
mango/tests/config_module/test_config.py
mango-1.0.2.dist-info/licenses/LICENSE
mango-1.0.2.dist-info/METADATA
mango-1.0.2.dist-info/WHEEL
mango-1.0.2.dist-info/top_level.txt
mango-1.0.2.dist-info/RECORD
