Metadata-Version: 2.4
Name: mango
Version: 1.0.2
Summary: Library with a collection of useful classes and methods to DRY
Author-email: baobab soluciones <mango@baobabsoluciones.es>
License: Apache Software License
Project-URL: repository, https://github.com/baobabsoluciones/mango
Classifier: Programming Language :: Python :: 3
Classifier: License :: OSI Approved :: Apache Software License
Classifier: Operating System :: OS Independent
Classifier: Development Status :: 4 - Beta
Requires-Python: >=3.10
License-File: LICENSE
Requires-Dist: certifi<2025.0.0,>=2024.7.4
Requires-Dist: charset-normalizer<4.0.0,>=3.3.0
Requires-Dist: et-xmlfile<2.0.0,>=1.1.0
Requires-Dist: fastjsonschema<3.0.0,>=2.18.1
Requires-Dist: idna<4.0.0,>=3.7
Requires-Dist: numpy<2.0.0,>=1.24.4
Requires-Dist: openpyxl<4.0.0,>=3.1.2
Requires-Dist: pydantic<3.0.0,>=2.4.2
Requires-Dist: python-dateutil<3.0.0,>=2.8.2
Requires-Dist: pytups<1.0.0,>=0.86.2
Requires-Dist: pytz<2024.0.0,>=2023.3.post1
Requires-Dist: requests<3.0.0,>=2.32.4
Requires-Dist: six<2.0.0,>=1.16.0
Requires-Dist: tqdm<5.0.0,>=4.66.3
Requires-Dist: urllib3<3.0.0,>=2.6.3
Requires-Dist: XlsxWriter<4.0.0,>=3.1.9
Provides-Extra: dev
Requires-Dist: coverage[toml]>=7.0; extra == "dev"
Provides-Extra: data
Requires-Dist: pandas<3.0.0,>=2.0.3; extra == "data"
Requires-Dist: polars<2.0.0,>=1.0.0; extra == "data"
Requires-Dist: scikit-learn<2.0.0,>=1.5.0; extra == "data"
Requires-Dist: pyomo<7.0.0,>=6.6.2; extra == "data"
Requires-Dist: tomli<3.0.0,>=2.0.1; python_version < "3.11" and extra == "data"
Dynamic: license-file
